<?xml version="1.0" encoding="UTF-8"?>
<CURVAS>
	<CURVA>
		<CUPS>ES0031408170539001WB0F</CUPS>
		<CLIENTE>4894</CLIENTE>
		<PERIODOMEDIDA>60</PERIODOMEDIDA>
		<FECHAMED>2018-01-11 01:00:00.000</FECHAMED>
		<ACTIVAEINC>11</ACTIVAEINC>
		<ACTIVASINC>0</ACTIVASINC>
		<REACTIVA1INC>1</REACTIVA1INC>
		<REACTIVA2INC>7</REACTIVA2INC>
		<REACTIVA3INC>0</REACTIVA3INC>
		<REACTIVA4INC>0</REACTIVA4INC>
		<FLAGS>0</FLAGS>
	</CURVA>
	<CURVA>
		<CUPS>ES0031408170539001WB0F</CUPS>
		<CLIENTE>4894</CLIENTE>
		<PERIODOMEDIDA>60</PERIODOMEDIDA>
		<FECHAMED>2018-01-11 02:00:00.000</FECHAMED>
		<ACTIVAEINC>13</ACTIVAEINC>
		<ACTIVASINC>0</ACTIVASINC>
		<REACTIVA1INC>1</REACTIVA1INC>
		<REACTIVA2INC>6</REACTIVA2INC>
		<REACTIVA3INC>0</REACTIVA3INC>
		<REACTIVA4INC>0</REACTIVA4INC>
		<FLAGS>0</FLAGS>
	</CURVA>
	<CURVA>
		<CUPS>ES0031408170539001WB0F</CUPS>
		<CLIENTE>4894</CLIENTE>
		<PERIODOMEDIDA>60</PERIODOMEDIDA>
		<FECHAMED>2018-01-11 03:00:00.000</FECHAMED>
		<ACTIVAEINC>11</ACTIVAEINC>
		<ACTIVASINC>0</ACTIVASINC>
		<REACTIVA1INC>0</REACTIVA1INC>
		<REACTIVA2INC>7</REACTIVA2INC>
		<REACTIVA3INC>0</REACTIVA3INC>
		<REACTIVA4INC>0</REACTIVA4INC>
		<FLAGS>0</FLAGS>
	</CURVA>
	<CURVA>
		<CUPS>ES0031408170539001WB0F</CUPS>
		<CLIENTE>4894</CLIENTE>
		<PERIODOMEDIDA>60</PERIODOMEDIDA>
		<FECHAMED>2018-01-11 04:00:00.000</FECHAMED>
		<ACTIVAEINC>12</ACTIVAEINC>
		<ACTIVASINC>0</ACTIVASINC>
		<REACTIVA1INC>1</REACTIVA1INC>
		<REACTIVA2INC>6</REACTIVA2INC>
		<REACTIVA3INC>0</REACTIVA3INC>
		<REACTIVA4INC>0</REACTIVA4INC>
		<FLAGS>0</FLAGS>
	</CURVA>
	<CURVA>
		<CUPS>ES0031408170539001WB0F</CUPS>
		<CLIENTE>4894</CLIENTE>
		<PERIODOMEDIDA>60</PERIODOMEDIDA>
		<FECHAMED>2018-01-11 05:00:00.000</FECHAMED>
		<ACTIVAEINC>12</ACTIVAEINC>
		<ACTIVASINC>0</ACTIVASINC>
		<REACTIVA1INC>1</REACTIVA1INC>
		<REACTIVA2INC>7</REACTIVA2INC>
		<REACTIVA3INC>0</REACTIVA3INC>
		<REACTIVA4INC>0</REACTIVA4INC>
		<FLAGS>0</FLAGS>
	</CURVA>
	<CURVA>
		<CUPS>ES0031408170539001WB0F</CUPS>
		<CLIENTE>4894</CLIENTE>
		<PERIODOMEDIDA>60</PERIODOMEDIDA>
		<FECHAMED>2018-01-11 06:00:00.000</FECHAMED>
		<ACTIVAEINC>11</ACTIVAEINC>
		<ACTIVASINC>0</ACTIVASINC>
		<REACTIVA1INC>1</REACTIVA1INC>
		<REACTIVA2INC>7</REACTIVA2INC>
		<REACTIVA3INC>0</REACTIVA3INC>
		<REACTIVA4INC>0</REACTIVA4INC>
		<FLAGS>0</FLAGS>
	</CURVA>
	<CURVA>
		<CUPS>ES0031408170539001WB0F</CUPS>
		<CLIENTE>4894</CLIENTE>
		<PERIODOMEDIDA>60</PERIODOMEDIDA>
		<FECHAMED>2018-01-11 07:00:00.000</FECHAMED>
		<ACTIVAEINC>18</ACTIVAEINC>
		<ACTIVASINC>0</ACTIVASINC>
		<REACTIVA1INC>1</REACTIVA1INC>
		<REACTIVA2INC>6</REACTIVA2INC>
		<REACTIVA3INC>0</REACTIVA3INC>
		<REACTIVA4INC>0</REACTIVA4INC>
		<FLAGS>0</FLAGS>
	</CURVA>
	<CURVA>
		<CUPS>ES0031408170539001WB0F</CUPS>
		<CLIENTE>4894</CLIENTE>
		<PERIODOMEDIDA>60</PERIODOMEDIDA>
		<FECHAMED>2018-01-11 08:00:00.000</FECHAMED>
		<ACTIVAEINC>73</ACTIVAEINC>
		<ACTIVASINC>0</ACTIVASINC>
		<REACTIVA1INC>6</REACTIVA1INC>
		<REACTIVA2INC>0</REACTIVA2INC>
		<REACTIVA3INC>0</REACTIVA3INC>
		<REACTIVA4INC>0</REACTIVA4INC>
		<FLAGS>0</FLAGS>
	</CURVA>
	<CURVA>
		<CUPS>ES0031408170539001WB0F</CUPS>
		<CLIENTE>4894</CLIENTE>
		<PERIODOMEDIDA>60</PERIODOMEDIDA>
		<FECHAMED>2018-01-11 09:00:00.000</FECHAMED>
		<ACTIVAEINC>87</ACTIVAEINC>
		<ACTIVASINC>0</ACTIVASINC>
		<REACTIVA1INC>7</REACTIVA1INC>
		<REACTIVA2INC>1</REACTIVA2INC>
		<REACTIVA3INC>0</REACTIVA3INC>
		<REACTIVA4INC>0</REACTIVA4INC>
		<FLAGS>0</FLAGS>
	</CURVA>
	<CURVA>
		<CUPS>ES0031408170539001WB0F</CUPS>
		<CLIENTE>4894</CLIENTE>
		<PERIODOMEDIDA>60</PERIODOMEDIDA>
		<FECHAMED>2018-01-11 10:00:00.000</FECHAMED>
		<ACTIVAEINC>77</ACTIVAEINC>
		<ACTIVASINC>0</ACTIVASINC>
		<REACTIVA1INC>4</REACTIVA1INC>
		<REACTIVA2INC>1</REACTIVA2INC>
		<REACTIVA3INC>0</REACTIVA3INC>
		<REACTIVA4INC>0</REACTIVA4INC>
		<FLAGS>0</FLAGS>
	</CURVA>
	<CURVA>
		<CUPS>ES0031408170539001WB0F</CUPS>
		<CLIENTE>4894</CLIENTE>
		<PERIODOMEDIDA>60</PERIODOMEDIDA>
		<FECHAMED>2018-01-11 11:00:00.000</FECHAMED>
		<ACTIVAEINC>82</ACTIVAEINC>
		<ACTIVASINC>0</ACTIVASINC>
		<REACTIVA1INC>7</REACTIVA1INC>
		<REACTIVA2INC>1</REACTIVA2INC>
		<REACTIVA3INC>0</REACTIVA3INC>
		<REACTIVA4INC>0</REACTIVA4INC>
		<FLAGS>0</FLAGS>
	</CURVA>
	<CURVA>
		<CUPS>ES0031408170539001WB0F</CUPS>
		<CLIENTE>4894</CLIENTE>
		<PERIODOMEDIDA>60</PERIODOMEDIDA>
		<FECHAMED>2018-01-11 12:00:00.000</FECHAMED>
		<ACTIVAEINC>84</ACTIVAEINC>
		<ACTIVASINC>0</ACTIVASINC>
		<REACTIVA1INC>7</REACTIVA1INC>
		<REACTIVA2INC>1</REACTIVA2INC>
		<REACTIVA3INC>0</REACTIVA3INC>
		<REACTIVA4INC>0</REACTIVA4INC>
		<FLAGS>0</FLAGS>
	</CURVA>
	<CURVA>
		<CUPS>ES0031408170539001WB0F</CUPS>
		<CLIENTE>4894</CLIENTE>
		<PERIODOMEDIDA>60</PERIODOMEDIDA>
		<FECHAMED>2018-01-11 13:00:00.000</FECHAMED>
		<ACTIVAEINC>78</ACTIVAEINC>
		<ACTIVASINC>0</ACTIVASINC>
		<REACTIVA1INC>6</REACTIVA1INC>
		<REACTIVA2INC>1</REACTIVA2INC>
		<REACTIVA3INC>0</REACTIVA3INC>
		<REACTIVA4INC>0</REACTIVA4INC>
		<FLAGS>0</FLAGS>
	</CURVA>
	<CURVA>
		<CUPS>ES0031408170539001WB0F</CUPS>
		<CLIENTE>4894</CLIENTE>
		<PERIODOMEDIDA>60</PERIODOMEDIDA>
		<FECHAMED>2018-01-11 14:00:00.000</FECHAMED>
		<ACTIVAEINC>76</ACTIVAEINC>
		<ACTIVASINC>0</ACTIVASINC>
		<REACTIVA1INC>10</REACTIVA1INC>
		<REACTIVA2INC>0</REACTIVA2INC>
		<REACTIVA3INC>0</REACTIVA3INC>
		<REACTIVA4INC>0</REACTIVA4INC>
		<FLAGS>0</FLAGS>
	</CURVA>
	<CURVA>
		<CUPS>ES0031408170539001WB0F</CUPS>
		<CLIENTE>4894</CLIENTE>
		<PERIODOMEDIDA>60</PERIODOMEDIDA>
		<FECHAMED>2018-01-11 15:00:00.000</FECHAMED>
		<ACTIVAEINC>77</ACTIVAEINC>
		<ACTIVASINC>0</ACTIVASINC>
		<REACTIVA1INC>12</REACTIVA1INC>
		<REACTIVA2INC>0</REACTIVA2INC>
		<REACTIVA3INC>0</REACTIVA3INC>
		<REACTIVA4INC>0</REACTIVA4INC>
		<FLAGS>0</FLAGS>
	</CURVA>
	<CURVA>
		<CUPS>ES0031408170539001WB0F</CUPS>
		<CLIENTE>4894</CLIENTE>
		<PERIODOMEDIDA>60</PERIODOMEDIDA>
		<FECHAMED>2018-01-11 16:00:00.000</FECHAMED>
		<ACTIVAEINC>62</ACTIVAEINC>
		<ACTIVASINC>0</ACTIVASINC>
		<REACTIVA1INC>9</REACTIVA1INC>
		<REACTIVA2INC>1</REACTIVA2INC>
		<REACTIVA3INC>0</REACTIVA3INC>
		<REACTIVA4INC>0</REACTIVA4INC>
		<FLAGS>0</FLAGS>
	</CURVA>
	<CURVA>
		<CUPS>ES0031408170539001WB0F</CUPS>
		<CLIENTE>4894</CLIENTE>
		<PERIODOMEDIDA>60</PERIODOMEDIDA>
		<FECHAMED>2018-01-11 17:00:00.000</FECHAMED>
		<ACTIVAEINC>51</ACTIVAEINC>
		<ACTIVASINC>0</ACTIVASINC>
		<REACTIVA1INC>6</REACTIVA1INC>
		<REACTIVA2INC>0</REACTIVA2INC>
		<REACTIVA3INC>0</REACTIVA3INC>
		<REACTIVA4INC>0</REACTIVA4INC>
		<FLAGS>0</FLAGS>
	</CURVA>
	<CURVA>
		<CUPS>ES0031408170539001WB0F</CUPS>
		<CLIENTE>4894</CLIENTE>
		<PERIODOMEDIDA>60</PERIODOMEDIDA>
		<FECHAMED>2018-01-11 18:00:00.000</FECHAMED>
		<ACTIVAEINC>52</ACTIVAEINC>
		<ACTIVASINC>0</ACTIVASINC>
		<REACTIVA1INC>8</REACTIVA1INC>
		<REACTIVA2INC>1</REACTIVA2INC>
		<REACTIVA3INC>0</REACTIVA3INC>
		<REACTIVA4INC>0</REACTIVA4INC>
		<FLAGS>0</FLAGS>
	</CURVA>
	<CURVA>
		<CUPS>ES0031408170539001WB0F</CUPS>
		<CLIENTE>4894</CLIENTE>
		<PERIODOMEDIDA>60</PERIODOMEDIDA>
		<FECHAMED>2018-01-11 19:00:00.000</FECHAMED>
		<ACTIVAEINC>49</ACTIVAEINC>
		<ACTIVASINC>0</ACTIVASINC>
		<REACTIVA1INC>5</REACTIVA1INC>
		<REACTIVA2INC>1</REACTIVA2INC>
		<REACTIVA3INC>0</REACTIVA3INC>
		<REACTIVA4INC>0</REACTIVA4INC>
		<FLAGS>0</FLAGS>
	</CURVA>
	<CURVA>
		<CUPS>ES0031408170539001WB0F</CUPS>
		<CLIENTE>4894</CLIENTE>
		<PERIODOMEDIDA>60</PERIODOMEDIDA>
		<FECHAMED>2018-01-11 20:00:00.000</FECHAMED>
		<ACTIVAEINC>53</ACTIVAEINC>
		<ACTIVASINC>0</ACTIVASINC>
		<REACTIVA1INC>6</REACTIVA1INC>
		<REACTIVA2INC>1</REACTIVA2INC>
		<REACTIVA3INC>0</REACTIVA3INC>
		<REACTIVA4INC>0</REACTIVA4INC>
		<FLAGS>0</FLAGS>
	</CURVA>
	<CURVA>
		<CUPS>ES0031408170539001WB0F</CUPS>
		<CLIENTE>4894</CLIENTE>
		<PERIODOMEDIDA>60</PERIODOMEDIDA>
		<FECHAMED>2018-01-11 21:00:00.000</FECHAMED>
		<ACTIVAEINC>58</ACTIVAEINC>
		<ACTIVASINC>0</ACTIVASINC>
		<REACTIVA1INC>6</REACTIVA1INC>
		<REACTIVA2INC>1</REACTIVA2INC>
		<REACTIVA3INC>0</REACTIVA3INC>
		<REACTIVA4INC>0</REACTIVA4INC>
		<FLAGS>0</FLAGS>
	</CURVA>
	<CURVA>
		<CUPS>ES0031408170539001WB0F</CUPS>
		<CLIENTE>4894</CLIENTE>
		<PERIODOMEDIDA>60</PERIODOMEDIDA>
		<FECHAMED>2018-01-11 22:00:00.000</FECHAMED>
		<ACTIVAEINC>25</ACTIVAEINC>
		<ACTIVASINC>0</ACTIVASINC>
		<REACTIVA1INC>2</REACTIVA1INC>
		<REACTIVA2INC>3</REACTIVA2INC>
		<REACTIVA3INC>0</REACTIVA3INC>
		<REACTIVA4INC>0</REACTIVA4INC>
		<FLAGS>0</FLAGS>
	</CURVA>
	<CURVA>
		<CUPS>ES0031408170539001WB0F</CUPS>
		<CLIENTE>4894</CLIENTE>
		<PERIODOMEDIDA>60</PERIODOMEDIDA>
		<FECHAMED>2018-01-11 23:00:00.000</FECHAMED>
		<ACTIVAEINC>15</ACTIVAEINC>
		<ACTIVASINC>0</ACTIVASINC>
		<REACTIVA1INC>2</REACTIVA1INC>
		<REACTIVA2INC>5</REACTIVA2INC>
		<REACTIVA3INC>0</REACTIVA3INC>
		<REACTIVA4INC>0</REACTIVA4INC>
		<FLAGS>0</FLAGS>
	</CURVA>
	<CURVA>
		<CUPS>ES0031408170539001WB0F</CUPS>
		<CLIENTE>4894</CLIENTE>
		<PERIODOMEDIDA>60</PERIODOMEDIDA>
		<FECHAMED>2018-01-12 00:00:00.000</FECHAMED>
		<ACTIVAEINC>13</ACTIVAEINC>
		<ACTIVASINC>0</ACTIVASINC>
		<REACTIVA1INC>1</REACTIVA1INC>
		<REACTIVA2INC>6</REACTIVA2INC>
		<REACTIVA3INC>0</REACTIVA3INC>
		<REACTIVA4INC>0</REACTIVA4INC>
		<FLAGS>0</FLAGS>
	</CURVA>
</CURVAS>
