<?xml version="1.0" encoding="UTF-8"?>
<CURVAS>
	<CURVA>
		<CUPS>ES0021000011689460PY0P</CUPS>
		<CLIENTE>4935</CLIENTE>
		<PERIODOMEDIDA>60</PERIODOMEDIDA>
		<FECHAMED>2018-01-05 01:00:00.000</FECHAMED>
		<ACTIVAEINC>117</ACTIVAEINC>
		<ACTIVASINC>0</ACTIVASINC>
		<REACTIVA1INC>1</REACTIVA1INC>
		<REACTIVA2INC>62</REACTIVA2INC>
		<REACTIVA3INC>0</REACTIVA3INC>
		<REACTIVA4INC>0</REACTIVA4INC>
		<FLAGS>0</FLAGS>
	</CURVA>
	<CURVA>
		<CUPS>ES0021000011689460PY0P</CUPS>
		<CLIENTE>4935</CLIENTE>
		<PERIODOMEDIDA>60</PERIODOMEDIDA>
		<FECHAMED>2018-01-05 02:00:00.000</FECHAMED>
		<ACTIVAEINC>117</ACTIVAEINC>
		<ACTIVASINC>0</ACTIVASINC>
		<REACTIVA1INC>0</REACTIVA1INC>
		<REACTIVA2INC>59</REACTIVA2INC>
		<REACTIVA3INC>0</REACTIVA3INC>
		<REACTIVA4INC>0</REACTIVA4INC>
		<FLAGS>0</FLAGS>
	</CURVA>
	<CURVA>
		<CUPS>ES0021000011689460PY0P</CUPS>
		<CLIENTE>4935</CLIENTE>
		<PERIODOMEDIDA>60</PERIODOMEDIDA>
		<FECHAMED>2018-01-05 03:00:00.000</FECHAMED>
		<ACTIVAEINC>117</ACTIVAEINC>
		<ACTIVASINC>0</ACTIVASINC>
		<REACTIVA1INC>0</REACTIVA1INC>
		<REACTIVA2INC>60</REACTIVA2INC>
		<REACTIVA3INC>0</REACTIVA3INC>
		<REACTIVA4INC>0</REACTIVA4INC>
		<FLAGS>0</FLAGS>
	</CURVA>
	<CURVA>
		<CUPS>ES0021000011689460PY0P</CUPS>
		<CLIENTE>4935</CLIENTE>
		<PERIODOMEDIDA>60</PERIODOMEDIDA>
		<FECHAMED>2018-01-05 04:00:00.000</FECHAMED>
		<ACTIVAEINC>118</ACTIVAEINC>
		<ACTIVASINC>0</ACTIVASINC>
		<REACTIVA1INC>1</REACTIVA1INC>
		<REACTIVA2INC>58</REACTIVA2INC>
		<REACTIVA3INC>0</REACTIVA3INC>
		<REACTIVA4INC>0</REACTIVA4INC>
		<FLAGS>0</FLAGS>
	</CURVA>
	<CURVA>
		<CUPS>ES0021000011689460PY0P</CUPS>
		<CLIENTE>4935</CLIENTE>
		<PERIODOMEDIDA>60</PERIODOMEDIDA>
		<FECHAMED>2018-01-05 05:00:00.000</FECHAMED>
		<ACTIVAEINC>119</ACTIVAEINC>
		<ACTIVASINC>0</ACTIVASINC>
		<REACTIVA1INC>0</REACTIVA1INC>
		<REACTIVA2INC>56</REACTIVA2INC>
		<REACTIVA3INC>0</REACTIVA3INC>
		<REACTIVA4INC>0</REACTIVA4INC>
		<FLAGS>0</FLAGS>
	</CURVA>
	<CURVA>
		<CUPS>ES0021000011689460PY0P</CUPS>
		<CLIENTE>4935</CLIENTE>
		<PERIODOMEDIDA>60</PERIODOMEDIDA>
		<FECHAMED>2018-01-05 06:00:00.000</FECHAMED>
		<ACTIVAEINC>124</ACTIVAEINC>
		<ACTIVASINC>0</ACTIVASINC>
		<REACTIVA1INC>0</REACTIVA1INC>
		<REACTIVA2INC>55</REACTIVA2INC>
		<REACTIVA3INC>0</REACTIVA3INC>
		<REACTIVA4INC>0</REACTIVA4INC>
		<FLAGS>0</FLAGS>
	</CURVA>
	<CURVA>
		<CUPS>ES0021000011689460PY0P</CUPS>
		<CLIENTE>4935</CLIENTE>
		<PERIODOMEDIDA>60</PERIODOMEDIDA>
		<FECHAMED>2018-01-05 07:00:00.000</FECHAMED>
		<ACTIVAEINC>126</ACTIVAEINC>
		<ACTIVASINC>0</ACTIVASINC>
		<REACTIVA1INC>0</REACTIVA1INC>
		<REACTIVA2INC>63</REACTIVA2INC>
		<REACTIVA3INC>0</REACTIVA3INC>
		<REACTIVA4INC>0</REACTIVA4INC>
		<FLAGS>0</FLAGS>
	</CURVA>
	<CURVA>
		<CUPS>ES0021000011689460PY0P</CUPS>
		<CLIENTE>4935</CLIENTE>
		<PERIODOMEDIDA>60</PERIODOMEDIDA>
		<FECHAMED>2018-01-05 08:00:00.000</FECHAMED>
		<ACTIVAEINC>128</ACTIVAEINC>
		<ACTIVASINC>0</ACTIVASINC>
		<REACTIVA1INC>1</REACTIVA1INC>
		<REACTIVA2INC>59</REACTIVA2INC>
		<REACTIVA3INC>0</REACTIVA3INC>
		<REACTIVA4INC>0</REACTIVA4INC>
		<FLAGS>0</FLAGS>
	</CURVA>
	<CURVA>
		<CUPS>ES0021000011689460PY0P</CUPS>
		<CLIENTE>4935</CLIENTE>
		<PERIODOMEDIDA>60</PERIODOMEDIDA>
		<FECHAMED>2018-01-05 09:00:00.000</FECHAMED>
		<ACTIVAEINC>88</ACTIVAEINC>
		<ACTIVASINC>0</ACTIVASINC>
		<REACTIVA1INC>0</REACTIVA1INC>
		<REACTIVA2INC>41</REACTIVA2INC>
		<REACTIVA3INC>0</REACTIVA3INC>
		<REACTIVA4INC>0</REACTIVA4INC>
		<FLAGS>0</FLAGS>
	</CURVA>
	<CURVA>
		<CUPS>ES0021000011689460PY0P</CUPS>
		<CLIENTE>4935</CLIENTE>
		<PERIODOMEDIDA>60</PERIODOMEDIDA>
		<FECHAMED>2018-01-05 10:00:00.000</FECHAMED>
		<ACTIVAEINC>0</ACTIVAEINC>
		<ACTIVASINC>0</ACTIVASINC>
		<REACTIVA1INC>0</REACTIVA1INC>
		<REACTIVA2INC>0</REACTIVA2INC>
		<REACTIVA3INC>0</REACTIVA3INC>
		<REACTIVA4INC>0</REACTIVA4INC>
		<FLAGS>0</FLAGS>
	</CURVA>
	<CURVA>
		<CUPS>ES0021000011689460PY0P</CUPS>
		<CLIENTE>4935</CLIENTE>
		<PERIODOMEDIDA>60</PERIODOMEDIDA>
		<FECHAMED>2018-01-05 11:00:00.000</FECHAMED>
		<ACTIVAEINC>23</ACTIVAEINC>
		<ACTIVASINC>0</ACTIVASINC>
		<REACTIVA1INC>0</REACTIVA1INC>
		<REACTIVA2INC>40</REACTIVA2INC>
		<REACTIVA3INC>0</REACTIVA3INC>
		<REACTIVA4INC>0</REACTIVA4INC>
		<FLAGS>0</FLAGS>
	</CURVA>
	<CURVA>
		<CUPS>ES0021000011689460PY0P</CUPS>
		<CLIENTE>4935</CLIENTE>
		<PERIODOMEDIDA>60</PERIODOMEDIDA>
		<FECHAMED>2018-01-05 12:00:00.000</FECHAMED>
		<ACTIVAEINC>56</ACTIVAEINC>
		<ACTIVASINC>0</ACTIVASINC>
		<REACTIVA1INC>0</REACTIVA1INC>
		<REACTIVA2INC>96</REACTIVA2INC>
		<REACTIVA3INC>0</REACTIVA3INC>
		<REACTIVA4INC>0</REACTIVA4INC>
		<FLAGS>0</FLAGS>
	</CURVA>
	<CURVA>
		<CUPS>ES0021000011689460PY0P</CUPS>
		<CLIENTE>4935</CLIENTE>
		<PERIODOMEDIDA>60</PERIODOMEDIDA>
		<FECHAMED>2018-01-05 13:00:00.000</FECHAMED>
		<ACTIVAEINC>96</ACTIVAEINC>
		<ACTIVASINC>0</ACTIVASINC>
		<REACTIVA1INC>1</REACTIVA1INC>
		<REACTIVA2INC>52</REACTIVA2INC>
		<REACTIVA3INC>0</REACTIVA3INC>
		<REACTIVA4INC>0</REACTIVA4INC>
		<FLAGS>0</FLAGS>
	</CURVA>
	<CURVA>
		<CUPS>ES0021000011689460PY0P</CUPS>
		<CLIENTE>4935</CLIENTE>
		<PERIODOMEDIDA>60</PERIODOMEDIDA>
		<FECHAMED>2018-01-05 14:00:00.000</FECHAMED>
		<ACTIVAEINC>98</ACTIVAEINC>
		<ACTIVASINC>0</ACTIVASINC>
		<REACTIVA1INC>0</REACTIVA1INC>
		<REACTIVA2INC>47</REACTIVA2INC>
		<REACTIVA3INC>0</REACTIVA3INC>
		<REACTIVA4INC>0</REACTIVA4INC>
		<FLAGS>0</FLAGS>
	</CURVA>
	<CURVA>
		<CUPS>ES0021000011689460PY0P</CUPS>
		<CLIENTE>4935</CLIENTE>
		<PERIODOMEDIDA>60</PERIODOMEDIDA>
		<FECHAMED>2018-01-05 15:00:00.000</FECHAMED>
		<ACTIVAEINC>98</ACTIVAEINC>
		<ACTIVASINC>0</ACTIVASINC>
		<REACTIVA1INC>0</REACTIVA1INC>
		<REACTIVA2INC>46</REACTIVA2INC>
		<REACTIVA3INC>0</REACTIVA3INC>
		<REACTIVA4INC>0</REACTIVA4INC>
		<FLAGS>0</FLAGS>
	</CURVA>
	<CURVA>
		<CUPS>ES0021000011689460PY0P</CUPS>
		<CLIENTE>4935</CLIENTE>
		<PERIODOMEDIDA>60</PERIODOMEDIDA>
		<FECHAMED>2018-01-05 16:00:00.000</FECHAMED>
		<ACTIVAEINC>84</ACTIVAEINC>
		<ACTIVASINC>0</ACTIVASINC>
		<REACTIVA1INC>1</REACTIVA1INC>
		<REACTIVA2INC>64</REACTIVA2INC>
		<REACTIVA3INC>0</REACTIVA3INC>
		<REACTIVA4INC>0</REACTIVA4INC>
		<FLAGS>0</FLAGS>
	</CURVA>
	<CURVA>
		<CUPS>ES0021000011689460PY0P</CUPS>
		<CLIENTE>4935</CLIENTE>
		<PERIODOMEDIDA>60</PERIODOMEDIDA>
		<FECHAMED>2018-01-05 17:00:00.000</FECHAMED>
		<ACTIVAEINC>93</ACTIVAEINC>
		<ACTIVASINC>0</ACTIVASINC>
		<REACTIVA1INC>0</REACTIVA1INC>
		<REACTIVA2INC>64</REACTIVA2INC>
		<REACTIVA3INC>0</REACTIVA3INC>
		<REACTIVA4INC>0</REACTIVA4INC>
		<FLAGS>0</FLAGS>
	</CURVA>
	<CURVA>
		<CUPS>ES0021000011689460PY0P</CUPS>
		<CLIENTE>4935</CLIENTE>
		<PERIODOMEDIDA>60</PERIODOMEDIDA>
		<FECHAMED>2018-01-05 18:00:00.000</FECHAMED>
		<ACTIVAEINC>115</ACTIVAEINC>
		<ACTIVASINC>0</ACTIVASINC>
		<REACTIVA1INC>0</REACTIVA1INC>
		<REACTIVA2INC>58</REACTIVA2INC>
		<REACTIVA3INC>0</REACTIVA3INC>
		<REACTIVA4INC>0</REACTIVA4INC>
		<FLAGS>0</FLAGS>
	</CURVA>
	<CURVA>
		<CUPS>ES0021000011689460PY0P</CUPS>
		<CLIENTE>4935</CLIENTE>
		<PERIODOMEDIDA>60</PERIODOMEDIDA>
		<FECHAMED>2018-01-05 19:00:00.000</FECHAMED>
		<ACTIVAEINC>121</ACTIVAEINC>
		<ACTIVASINC>0</ACTIVASINC>
		<REACTIVA1INC>1</REACTIVA1INC>
		<REACTIVA2INC>63</REACTIVA2INC>
		<REACTIVA3INC>0</REACTIVA3INC>
		<REACTIVA4INC>0</REACTIVA4INC>
		<FLAGS>0</FLAGS>
	</CURVA>
	<CURVA>
		<CUPS>ES0021000011689460PY0P</CUPS>
		<CLIENTE>4935</CLIENTE>
		<PERIODOMEDIDA>60</PERIODOMEDIDA>
		<FECHAMED>2018-01-05 20:00:00.000</FECHAMED>
		<ACTIVAEINC>119</ACTIVAEINC>
		<ACTIVASINC>0</ACTIVASINC>
		<REACTIVA1INC>0</REACTIVA1INC>
		<REACTIVA2INC>63</REACTIVA2INC>
		<REACTIVA3INC>0</REACTIVA3INC>
		<REACTIVA4INC>0</REACTIVA4INC>
		<FLAGS>0</FLAGS>
	</CURVA>
	<CURVA>
		<CUPS>ES0021000011689460PY0P</CUPS>
		<CLIENTE>4935</CLIENTE>
		<PERIODOMEDIDA>60</PERIODOMEDIDA>
		<FECHAMED>2018-01-05 21:00:00.000</FECHAMED>
		<ACTIVAEINC>120</ACTIVAEINC>
		<ACTIVASINC>0</ACTIVASINC>
		<REACTIVA1INC>0</REACTIVA1INC>
		<REACTIVA2INC>65</REACTIVA2INC>
		<REACTIVA3INC>0</REACTIVA3INC>
		<REACTIVA4INC>0</REACTIVA4INC>
		<FLAGS>0</FLAGS>
	</CURVA>
	<CURVA>
		<CUPS>ES0021000011689460PY0P</CUPS>
		<CLIENTE>4935</CLIENTE>
		<PERIODOMEDIDA>60</PERIODOMEDIDA>
		<FECHAMED>2018-01-05 22:00:00.000</FECHAMED>
		<ACTIVAEINC>116</ACTIVAEINC>
		<ACTIVASINC>0</ACTIVASINC>
		<REACTIVA1INC>0</REACTIVA1INC>
		<REACTIVA2INC>67</REACTIVA2INC>
		<REACTIVA3INC>0</REACTIVA3INC>
		<REACTIVA4INC>0</REACTIVA4INC>
		<FLAGS>0</FLAGS>
	</CURVA>
	<CURVA>
		<CUPS>ES0021000011689460PY0P</CUPS>
		<CLIENTE>4935</CLIENTE>
		<PERIODOMEDIDA>60</PERIODOMEDIDA>
		<FECHAMED>2018-01-05 23:00:00.000</FECHAMED>
		<ACTIVAEINC>112</ACTIVAEINC>
		<ACTIVASINC>0</ACTIVASINC>
		<REACTIVA1INC>1</REACTIVA1INC>
		<REACTIVA2INC>63</REACTIVA2INC>
		<REACTIVA3INC>0</REACTIVA3INC>
		<REACTIVA4INC>0</REACTIVA4INC>
		<FLAGS>0</FLAGS>
	</CURVA>
	<CURVA>
		<CUPS>ES0021000011689460PY0P</CUPS>
		<CLIENTE>4935</CLIENTE>
		<PERIODOMEDIDA>60</PERIODOMEDIDA>
		<FECHAMED>2018-01-06 00:00:00.000</FECHAMED>
		<ACTIVAEINC>110</ACTIVAEINC>
		<ACTIVASINC>0</ACTIVASINC>
		<REACTIVA1INC>0</REACTIVA1INC>
		<REACTIVA2INC>66</REACTIVA2INC>
		<REACTIVA3INC>0</REACTIVA3INC>
		<REACTIVA4INC>0</REACTIVA4INC>
		<FLAGS>0</FLAGS>
	</CURVA>
</CURVAS>
