<?xml version="1.0" encoding="UTF-8"?>
<CURVAS>
	<CURVA>
		<CUPS>ES0021000017346827HV0P</CUPS>
		<CLIENTE>1138</CLIENTE>
		<PERIODOMEDIDA>60</PERIODOMEDIDA>
		<FECHAMED>2018-01-08 01:00:00.000</FECHAMED>
		<ACTIVAEINC>10</ACTIVAEINC>
		<ACTIVASINC>0</ACTIVASINC>
		<REACTIVA1INC>0</REACTIVA1INC>
		<REACTIVA2INC>99</REACTIVA2INC>
		<REACTIVA3INC>0</REACTIVA3INC>
		<REACTIVA4INC>0</REACTIVA4INC>
		<FLAGS>0</FLAGS>
	</CURVA>
	<CURVA>
		<CUPS>ES0021000017346827HV0P</CUPS>
		<CLIENTE>1138</CLIENTE>
		<PERIODOMEDIDA>60</PERIODOMEDIDA>
		<FECHAMED>2018-01-08 02:00:00.000</FECHAMED>
		<ACTIVAEINC>10</ACTIVAEINC>
		<ACTIVASINC>0</ACTIVASINC>
		<REACTIVA1INC>0</REACTIVA1INC>
		<REACTIVA2INC>99</REACTIVA2INC>
		<REACTIVA3INC>0</REACTIVA3INC>
		<REACTIVA4INC>0</REACTIVA4INC>
		<FLAGS>0</FLAGS>
	</CURVA>
	<CURVA>
		<CUPS>ES0021000017346827HV0P</CUPS>
		<CLIENTE>1138</CLIENTE>
		<PERIODOMEDIDA>60</PERIODOMEDIDA>
		<FECHAMED>2018-01-08 03:00:00.000</FECHAMED>
		<ACTIVAEINC>10</ACTIVAEINC>
		<ACTIVASINC>0</ACTIVASINC>
		<REACTIVA1INC>0</REACTIVA1INC>
		<REACTIVA2INC>98</REACTIVA2INC>
		<REACTIVA3INC>0</REACTIVA3INC>
		<REACTIVA4INC>0</REACTIVA4INC>
		<FLAGS>0</FLAGS>
	</CURVA>
	<CURVA>
		<CUPS>ES0021000017346827HV0P</CUPS>
		<CLIENTE>1138</CLIENTE>
		<PERIODOMEDIDA>60</PERIODOMEDIDA>
		<FECHAMED>2018-01-08 04:00:00.000</FECHAMED>
		<ACTIVAEINC>10</ACTIVAEINC>
		<ACTIVASINC>0</ACTIVASINC>
		<REACTIVA1INC>0</REACTIVA1INC>
		<REACTIVA2INC>99</REACTIVA2INC>
		<REACTIVA3INC>0</REACTIVA3INC>
		<REACTIVA4INC>0</REACTIVA4INC>
		<FLAGS>0</FLAGS>
	</CURVA>
	<CURVA>
		<CUPS>ES0021000017346827HV0P</CUPS>
		<CLIENTE>1138</CLIENTE>
		<PERIODOMEDIDA>60</PERIODOMEDIDA>
		<FECHAMED>2018-01-08 05:00:00.000</FECHAMED>
		<ACTIVAEINC>10</ACTIVAEINC>
		<ACTIVASINC>0</ACTIVASINC>
		<REACTIVA1INC>0</REACTIVA1INC>
		<REACTIVA2INC>99</REACTIVA2INC>
		<REACTIVA3INC>0</REACTIVA3INC>
		<REACTIVA4INC>0</REACTIVA4INC>
		<FLAGS>0</FLAGS>
	</CURVA>
	<CURVA>
		<CUPS>ES0021000017346827HV0P</CUPS>
		<CLIENTE>1138</CLIENTE>
		<PERIODOMEDIDA>60</PERIODOMEDIDA>
		<FECHAMED>2018-01-08 06:00:00.000</FECHAMED>
		<ACTIVAEINC>10</ACTIVAEINC>
		<ACTIVASINC>0</ACTIVASINC>
		<REACTIVA1INC>0</REACTIVA1INC>
		<REACTIVA2INC>99</REACTIVA2INC>
		<REACTIVA3INC>0</REACTIVA3INC>
		<REACTIVA4INC>0</REACTIVA4INC>
		<FLAGS>0</FLAGS>
	</CURVA>
	<CURVA>
		<CUPS>ES0021000017346827HV0P</CUPS>
		<CLIENTE>1138</CLIENTE>
		<PERIODOMEDIDA>60</PERIODOMEDIDA>
		<FECHAMED>2018-01-08 07:00:00.000</FECHAMED>
		<ACTIVAEINC>14</ACTIVAEINC>
		<ACTIVASINC>0</ACTIVASINC>
		<REACTIVA1INC>0</REACTIVA1INC>
		<REACTIVA2INC>97</REACTIVA2INC>
		<REACTIVA3INC>0</REACTIVA3INC>
		<REACTIVA4INC>0</REACTIVA4INC>
		<FLAGS>0</FLAGS>
	</CURVA>
	<CURVA>
		<CUPS>ES0021000017346827HV0P</CUPS>
		<CLIENTE>1138</CLIENTE>
		<PERIODOMEDIDA>60</PERIODOMEDIDA>
		<FECHAMED>2018-01-08 08:00:00.000</FECHAMED>
		<ACTIVAEINC>42</ACTIVAEINC>
		<ACTIVASINC>0</ACTIVASINC>
		<REACTIVA1INC>0</REACTIVA1INC>
		<REACTIVA2INC>97</REACTIVA2INC>
		<REACTIVA3INC>0</REACTIVA3INC>
		<REACTIVA4INC>0</REACTIVA4INC>
		<FLAGS>0</FLAGS>
	</CURVA>
	<CURVA>
		<CUPS>ES0021000017346827HV0P</CUPS>
		<CLIENTE>1138</CLIENTE>
		<PERIODOMEDIDA>60</PERIODOMEDIDA>
		<FECHAMED>2018-01-08 09:00:00.000</FECHAMED>
		<ACTIVAEINC>66</ACTIVAEINC>
		<ACTIVASINC>0</ACTIVASINC>
		<REACTIVA1INC>0</REACTIVA1INC>
		<REACTIVA2INC>102</REACTIVA2INC>
		<REACTIVA3INC>0</REACTIVA3INC>
		<REACTIVA4INC>0</REACTIVA4INC>
		<FLAGS>0</FLAGS>
	</CURVA>
	<CURVA>
		<CUPS>ES0021000017346827HV0P</CUPS>
		<CLIENTE>1138</CLIENTE>
		<PERIODOMEDIDA>60</PERIODOMEDIDA>
		<FECHAMED>2018-01-08 10:00:00.000</FECHAMED>
		<ACTIVAEINC>102</ACTIVAEINC>
		<ACTIVASINC>0</ACTIVASINC>
		<REACTIVA1INC>0</REACTIVA1INC>
		<REACTIVA2INC>92</REACTIVA2INC>
		<REACTIVA3INC>0</REACTIVA3INC>
		<REACTIVA4INC>0</REACTIVA4INC>
		<FLAGS>0</FLAGS>
	</CURVA>
	<CURVA>
		<CUPS>ES0021000017346827HV0P</CUPS>
		<CLIENTE>1138</CLIENTE>
		<PERIODOMEDIDA>60</PERIODOMEDIDA>
		<FECHAMED>2018-01-08 11:00:00.000</FECHAMED>
		<ACTIVAEINC>128</ACTIVAEINC>
		<ACTIVASINC>0</ACTIVASINC>
		<REACTIVA1INC>0</REACTIVA1INC>
		<REACTIVA2INC>92</REACTIVA2INC>
		<REACTIVA3INC>0</REACTIVA3INC>
		<REACTIVA4INC>0</REACTIVA4INC>
		<FLAGS>0</FLAGS>
	</CURVA>
	<CURVA>
		<CUPS>ES0021000017346827HV0P</CUPS>
		<CLIENTE>1138</CLIENTE>
		<PERIODOMEDIDA>60</PERIODOMEDIDA>
		<FECHAMED>2018-01-08 12:00:00.000</FECHAMED>
		<ACTIVAEINC>185</ACTIVAEINC>
		<ACTIVASINC>0</ACTIVASINC>
		<REACTIVA1INC>0</REACTIVA1INC>
		<REACTIVA2INC>90</REACTIVA2INC>
		<REACTIVA3INC>0</REACTIVA3INC>
		<REACTIVA4INC>0</REACTIVA4INC>
		<FLAGS>0</FLAGS>
	</CURVA>
	<CURVA>
		<CUPS>ES0021000017346827HV0P</CUPS>
		<CLIENTE>1138</CLIENTE>
		<PERIODOMEDIDA>60</PERIODOMEDIDA>
		<FECHAMED>2018-01-08 13:00:00.000</FECHAMED>
		<ACTIVAEINC>218</ACTIVAEINC>
		<ACTIVASINC>0</ACTIVASINC>
		<REACTIVA1INC>0</REACTIVA1INC>
		<REACTIVA2INC>87</REACTIVA2INC>
		<REACTIVA3INC>0</REACTIVA3INC>
		<REACTIVA4INC>0</REACTIVA4INC>
		<FLAGS>0</FLAGS>
	</CURVA>
	<CURVA>
		<CUPS>ES0021000017346827HV0P</CUPS>
		<CLIENTE>1138</CLIENTE>
		<PERIODOMEDIDA>60</PERIODOMEDIDA>
		<FECHAMED>2018-01-08 14:00:00.000</FECHAMED>
		<ACTIVAEINC>206</ACTIVAEINC>
		<ACTIVASINC>0</ACTIVASINC>
		<REACTIVA1INC>0</REACTIVA1INC>
		<REACTIVA2INC>92</REACTIVA2INC>
		<REACTIVA3INC>0</REACTIVA3INC>
		<REACTIVA4INC>0</REACTIVA4INC>
		<FLAGS>0</FLAGS>
	</CURVA>
	<CURVA>
		<CUPS>ES0021000017346827HV0P</CUPS>
		<CLIENTE>1138</CLIENTE>
		<PERIODOMEDIDA>60</PERIODOMEDIDA>
		<FECHAMED>2018-01-08 15:00:00.000</FECHAMED>
		<ACTIVAEINC>225</ACTIVAEINC>
		<ACTIVASINC>0</ACTIVASINC>
		<REACTIVA1INC>0</REACTIVA1INC>
		<REACTIVA2INC>91</REACTIVA2INC>
		<REACTIVA3INC>0</REACTIVA3INC>
		<REACTIVA4INC>0</REACTIVA4INC>
		<FLAGS>0</FLAGS>
	</CURVA>
	<CURVA>
		<CUPS>ES0021000017346827HV0P</CUPS>
		<CLIENTE>1138</CLIENTE>
		<PERIODOMEDIDA>60</PERIODOMEDIDA>
		<FECHAMED>2018-01-08 16:00:00.000</FECHAMED>
		<ACTIVAEINC>248</ACTIVAEINC>
		<ACTIVASINC>0</ACTIVASINC>
		<REACTIVA1INC>0</REACTIVA1INC>
		<REACTIVA2INC>86</REACTIVA2INC>
		<REACTIVA3INC>0</REACTIVA3INC>
		<REACTIVA4INC>0</REACTIVA4INC>
		<FLAGS>0</FLAGS>
	</CURVA>
	<CURVA>
		<CUPS>ES0021000017346827HV0P</CUPS>
		<CLIENTE>1138</CLIENTE>
		<PERIODOMEDIDA>60</PERIODOMEDIDA>
		<FECHAMED>2018-01-08 17:00:00.000</FECHAMED>
		<ACTIVAEINC>263</ACTIVAEINC>
		<ACTIVASINC>0</ACTIVASINC>
		<REACTIVA1INC>0</REACTIVA1INC>
		<REACTIVA2INC>99</REACTIVA2INC>
		<REACTIVA3INC>0</REACTIVA3INC>
		<REACTIVA4INC>0</REACTIVA4INC>
		<FLAGS>0</FLAGS>
	</CURVA>
	<CURVA>
		<CUPS>ES0021000017346827HV0P</CUPS>
		<CLIENTE>1138</CLIENTE>
		<PERIODOMEDIDA>60</PERIODOMEDIDA>
		<FECHAMED>2018-01-08 18:00:00.000</FECHAMED>
		<ACTIVAEINC>300</ACTIVAEINC>
		<ACTIVASINC>0</ACTIVASINC>
		<REACTIVA1INC>0</REACTIVA1INC>
		<REACTIVA2INC>97</REACTIVA2INC>
		<REACTIVA3INC>0</REACTIVA3INC>
		<REACTIVA4INC>0</REACTIVA4INC>
		<FLAGS>0</FLAGS>
	</CURVA>
	<CURVA>
		<CUPS>ES0021000017346827HV0P</CUPS>
		<CLIENTE>1138</CLIENTE>
		<PERIODOMEDIDA>60</PERIODOMEDIDA>
		<FECHAMED>2018-01-08 19:00:00.000</FECHAMED>
		<ACTIVAEINC>327</ACTIVAEINC>
		<ACTIVASINC>0</ACTIVASINC>
		<REACTIVA1INC>0</REACTIVA1INC>
		<REACTIVA2INC>88</REACTIVA2INC>
		<REACTIVA3INC>0</REACTIVA3INC>
		<REACTIVA4INC>0</REACTIVA4INC>
		<FLAGS>0</FLAGS>
	</CURVA>
	<CURVA>
		<CUPS>ES0021000017346827HV0P</CUPS>
		<CLIENTE>1138</CLIENTE>
		<PERIODOMEDIDA>60</PERIODOMEDIDA>
		<FECHAMED>2018-01-08 20:00:00.000</FECHAMED>
		<ACTIVAEINC>284</ACTIVAEINC>
		<ACTIVASINC>0</ACTIVASINC>
		<REACTIVA1INC>0</REACTIVA1INC>
		<REACTIVA2INC>108</REACTIVA2INC>
		<REACTIVA3INC>0</REACTIVA3INC>
		<REACTIVA4INC>0</REACTIVA4INC>
		<FLAGS>0</FLAGS>
	</CURVA>
	<CURVA>
		<CUPS>ES0021000017346827HV0P</CUPS>
		<CLIENTE>1138</CLIENTE>
		<PERIODOMEDIDA>60</PERIODOMEDIDA>
		<FECHAMED>2018-01-08 21:00:00.000</FECHAMED>
		<ACTIVAEINC>281</ACTIVAEINC>
		<ACTIVASINC>0</ACTIVASINC>
		<REACTIVA1INC>0</REACTIVA1INC>
		<REACTIVA2INC>109</REACTIVA2INC>
		<REACTIVA3INC>0</REACTIVA3INC>
		<REACTIVA4INC>0</REACTIVA4INC>
		<FLAGS>0</FLAGS>
	</CURVA>
	<CURVA>
		<CUPS>ES0021000017346827HV0P</CUPS>
		<CLIENTE>1138</CLIENTE>
		<PERIODOMEDIDA>60</PERIODOMEDIDA>
		<FECHAMED>2018-01-08 22:00:00.000</FECHAMED>
		<ACTIVAEINC>279</ACTIVAEINC>
		<ACTIVASINC>0</ACTIVASINC>
		<REACTIVA1INC>0</REACTIVA1INC>
		<REACTIVA2INC>111</REACTIVA2INC>
		<REACTIVA3INC>0</REACTIVA3INC>
		<REACTIVA4INC>0</REACTIVA4INC>
		<FLAGS>0</FLAGS>
	</CURVA>
	<CURVA>
		<CUPS>ES0021000017346827HV0P</CUPS>
		<CLIENTE>1138</CLIENTE>
		<PERIODOMEDIDA>60</PERIODOMEDIDA>
		<FECHAMED>2018-01-08 23:00:00.000</FECHAMED>
		<ACTIVAEINC>282</ACTIVAEINC>
		<ACTIVASINC>0</ACTIVASINC>
		<REACTIVA1INC>0</REACTIVA1INC>
		<REACTIVA2INC>109</REACTIVA2INC>
		<REACTIVA3INC>0</REACTIVA3INC>
		<REACTIVA4INC>0</REACTIVA4INC>
		<FLAGS>0</FLAGS>
	</CURVA>
	<CURVA>
		<CUPS>ES0021000017346827HV0P</CUPS>
		<CLIENTE>1138</CLIENTE>
		<PERIODOMEDIDA>60</PERIODOMEDIDA>
		<FECHAMED>2018-01-09 00:00:00.000</FECHAMED>
		<ACTIVAEINC>286</ACTIVAEINC>
		<ACTIVASINC>0</ACTIVASINC>
		<REACTIVA1INC>0</REACTIVA1INC>
		<REACTIVA2INC>109</REACTIVA2INC>
		<REACTIVA3INC>0</REACTIVA3INC>
		<REACTIVA4INC>0</REACTIVA4INC>
		<FLAGS>0</FLAGS>
	</CURVA>
</CURVAS>
