<?xml version="1.0" encoding="UTF-8"?>
<CURVAS>
	<CURVA>
		<CUPS>ES0031405299528001AY0F</CUPS>
		<CLIENTE>1680</CLIENTE>
		<PERIODOMEDIDA>60</PERIODOMEDIDA>
		<FECHAMED>2018-01-13 01:00:00.000</FECHAMED>
		<ACTIVAEINC>63</ACTIVAEINC>
		<ACTIVASINC>0</ACTIVASINC>
		<REACTIVA1INC>42</REACTIVA1INC>
		<REACTIVA2INC>0</REACTIVA2INC>
		<REACTIVA3INC>0</REACTIVA3INC>
		<REACTIVA4INC>0</REACTIVA4INC>
		<FLAGS>0</FLAGS>
	</CURVA>
	<CURVA>
		<CUPS>ES0031405299528001AY0F</CUPS>
		<CLIENTE>1680</CLIENTE>
		<PERIODOMEDIDA>60</PERIODOMEDIDA>
		<FECHAMED>2018-01-13 02:00:00.000</FECHAMED>
		<ACTIVAEINC>63</ACTIVAEINC>
		<ACTIVASINC>0</ACTIVASINC>
		<REACTIVA1INC>42</REACTIVA1INC>
		<REACTIVA2INC>0</REACTIVA2INC>
		<REACTIVA3INC>0</REACTIVA3INC>
		<REACTIVA4INC>0</REACTIVA4INC>
		<FLAGS>0</FLAGS>
	</CURVA>
	<CURVA>
		<CUPS>ES0031405299528001AY0F</CUPS>
		<CLIENTE>1680</CLIENTE>
		<PERIODOMEDIDA>60</PERIODOMEDIDA>
		<FECHAMED>2018-01-13 03:00:00.000</FECHAMED>
		<ACTIVAEINC>63</ACTIVAEINC>
		<ACTIVASINC>0</ACTIVASINC>
		<REACTIVA1INC>43</REACTIVA1INC>
		<REACTIVA2INC>0</REACTIVA2INC>
		<REACTIVA3INC>0</REACTIVA3INC>
		<REACTIVA4INC>0</REACTIVA4INC>
		<FLAGS>0</FLAGS>
	</CURVA>
	<CURVA>
		<CUPS>ES0031405299528001AY0F</CUPS>
		<CLIENTE>1680</CLIENTE>
		<PERIODOMEDIDA>60</PERIODOMEDIDA>
		<FECHAMED>2018-01-13 04:00:00.000</FECHAMED>
		<ACTIVAEINC>55</ACTIVAEINC>
		<ACTIVASINC>0</ACTIVASINC>
		<REACTIVA1INC>40</REACTIVA1INC>
		<REACTIVA2INC>0</REACTIVA2INC>
		<REACTIVA3INC>0</REACTIVA3INC>
		<REACTIVA4INC>0</REACTIVA4INC>
		<FLAGS>0</FLAGS>
	</CURVA>
	<CURVA>
		<CUPS>ES0031405299528001AY0F</CUPS>
		<CLIENTE>1680</CLIENTE>
		<PERIODOMEDIDA>60</PERIODOMEDIDA>
		<FECHAMED>2018-01-13 05:00:00.000</FECHAMED>
		<ACTIVAEINC>41</ACTIVAEINC>
		<ACTIVASINC>0</ACTIVASINC>
		<REACTIVA1INC>31</REACTIVA1INC>
		<REACTIVA2INC>0</REACTIVA2INC>
		<REACTIVA3INC>0</REACTIVA3INC>
		<REACTIVA4INC>0</REACTIVA4INC>
		<FLAGS>0</FLAGS>
	</CURVA>
	<CURVA>
		<CUPS>ES0031405299528001AY0F</CUPS>
		<CLIENTE>1680</CLIENTE>
		<PERIODOMEDIDA>60</PERIODOMEDIDA>
		<FECHAMED>2018-01-13 06:00:00.000</FECHAMED>
		<ACTIVAEINC>14</ACTIVAEINC>
		<ACTIVASINC>0</ACTIVASINC>
		<REACTIVA1INC>13</REACTIVA1INC>
		<REACTIVA2INC>0</REACTIVA2INC>
		<REACTIVA3INC>0</REACTIVA3INC>
		<REACTIVA4INC>0</REACTIVA4INC>
		<FLAGS>0</FLAGS>
	</CURVA>
	<CURVA>
		<CUPS>ES0031405299528001AY0F</CUPS>
		<CLIENTE>1680</CLIENTE>
		<PERIODOMEDIDA>60</PERIODOMEDIDA>
		<FECHAMED>2018-01-13 07:00:00.000</FECHAMED>
		<ACTIVAEINC>10</ACTIVAEINC>
		<ACTIVASINC>0</ACTIVASINC>
		<REACTIVA1INC>11</REACTIVA1INC>
		<REACTIVA2INC>0</REACTIVA2INC>
		<REACTIVA3INC>0</REACTIVA3INC>
		<REACTIVA4INC>0</REACTIVA4INC>
		<FLAGS>0</FLAGS>
	</CURVA>
	<CURVA>
		<CUPS>ES0031405299528001AY0F</CUPS>
		<CLIENTE>1680</CLIENTE>
		<PERIODOMEDIDA>60</PERIODOMEDIDA>
		<FECHAMED>2018-01-13 08:00:00.000</FECHAMED>
		<ACTIVAEINC>11</ACTIVAEINC>
		<ACTIVASINC>0</ACTIVASINC>
		<REACTIVA1INC>11</REACTIVA1INC>
		<REACTIVA2INC>0</REACTIVA2INC>
		<REACTIVA3INC>0</REACTIVA3INC>
		<REACTIVA4INC>0</REACTIVA4INC>
		<FLAGS>0</FLAGS>
	</CURVA>
	<CURVA>
		<CUPS>ES0031405299528001AY0F</CUPS>
		<CLIENTE>1680</CLIENTE>
		<PERIODOMEDIDA>60</PERIODOMEDIDA>
		<FECHAMED>2018-01-13 09:00:00.000</FECHAMED>
		<ACTIVAEINC>14</ACTIVAEINC>
		<ACTIVASINC>0</ACTIVASINC>
		<REACTIVA1INC>15</REACTIVA1INC>
		<REACTIVA2INC>0</REACTIVA2INC>
		<REACTIVA3INC>0</REACTIVA3INC>
		<REACTIVA4INC>0</REACTIVA4INC>
		<FLAGS>0</FLAGS>
	</CURVA>
	<CURVA>
		<CUPS>ES0031405299528001AY0F</CUPS>
		<CLIENTE>1680</CLIENTE>
		<PERIODOMEDIDA>60</PERIODOMEDIDA>
		<FECHAMED>2018-01-13 10:00:00.000</FECHAMED>
		<ACTIVAEINC>14</ACTIVAEINC>
		<ACTIVASINC>0</ACTIVASINC>
		<REACTIVA1INC>15</REACTIVA1INC>
		<REACTIVA2INC>0</REACTIVA2INC>
		<REACTIVA3INC>0</REACTIVA3INC>
		<REACTIVA4INC>0</REACTIVA4INC>
		<FLAGS>0</FLAGS>
	</CURVA>
	<CURVA>
		<CUPS>ES0031405299528001AY0F</CUPS>
		<CLIENTE>1680</CLIENTE>
		<PERIODOMEDIDA>60</PERIODOMEDIDA>
		<FECHAMED>2018-01-13 11:00:00.000</FECHAMED>
		<ACTIVAEINC>14</ACTIVAEINC>
		<ACTIVASINC>0</ACTIVASINC>
		<REACTIVA1INC>14</REACTIVA1INC>
		<REACTIVA2INC>0</REACTIVA2INC>
		<REACTIVA3INC>0</REACTIVA3INC>
		<REACTIVA4INC>0</REACTIVA4INC>
		<FLAGS>0</FLAGS>
	</CURVA>
	<CURVA>
		<CUPS>ES0031405299528001AY0F</CUPS>
		<CLIENTE>1680</CLIENTE>
		<PERIODOMEDIDA>60</PERIODOMEDIDA>
		<FECHAMED>2018-01-13 12:00:00.000</FECHAMED>
		<ACTIVAEINC>33</ACTIVAEINC>
		<ACTIVASINC>0</ACTIVASINC>
		<REACTIVA1INC>23</REACTIVA1INC>
		<REACTIVA2INC>0</REACTIVA2INC>
		<REACTIVA3INC>0</REACTIVA3INC>
		<REACTIVA4INC>0</REACTIVA4INC>
		<FLAGS>0</FLAGS>
	</CURVA>
	<CURVA>
		<CUPS>ES0031405299528001AY0F</CUPS>
		<CLIENTE>1680</CLIENTE>
		<PERIODOMEDIDA>60</PERIODOMEDIDA>
		<FECHAMED>2018-01-13 13:00:00.000</FECHAMED>
		<ACTIVAEINC>67</ACTIVAEINC>
		<ACTIVASINC>0</ACTIVASINC>
		<REACTIVA1INC>50</REACTIVA1INC>
		<REACTIVA2INC>0</REACTIVA2INC>
		<REACTIVA3INC>0</REACTIVA3INC>
		<REACTIVA4INC>0</REACTIVA4INC>
		<FLAGS>0</FLAGS>
	</CURVA>
	<CURVA>
		<CUPS>ES0031405299528001AY0F</CUPS>
		<CLIENTE>1680</CLIENTE>
		<PERIODOMEDIDA>60</PERIODOMEDIDA>
		<FECHAMED>2018-01-13 14:00:00.000</FECHAMED>
		<ACTIVAEINC>69</ACTIVAEINC>
		<ACTIVASINC>0</ACTIVASINC>
		<REACTIVA1INC>41</REACTIVA1INC>
		<REACTIVA2INC>0</REACTIVA2INC>
		<REACTIVA3INC>0</REACTIVA3INC>
		<REACTIVA4INC>0</REACTIVA4INC>
		<FLAGS>0</FLAGS>
	</CURVA>
	<CURVA>
		<CUPS>ES0031405299528001AY0F</CUPS>
		<CLIENTE>1680</CLIENTE>
		<PERIODOMEDIDA>60</PERIODOMEDIDA>
		<FECHAMED>2018-01-13 15:00:00.000</FECHAMED>
		<ACTIVAEINC>62</ACTIVAEINC>
		<ACTIVASINC>0</ACTIVASINC>
		<REACTIVA1INC>39</REACTIVA1INC>
		<REACTIVA2INC>0</REACTIVA2INC>
		<REACTIVA3INC>0</REACTIVA3INC>
		<REACTIVA4INC>0</REACTIVA4INC>
		<FLAGS>0</FLAGS>
	</CURVA>
	<CURVA>
		<CUPS>ES0031405299528001AY0F</CUPS>
		<CLIENTE>1680</CLIENTE>
		<PERIODOMEDIDA>60</PERIODOMEDIDA>
		<FECHAMED>2018-01-13 16:00:00.000</FECHAMED>
		<ACTIVAEINC>63</ACTIVAEINC>
		<ACTIVASINC>0</ACTIVASINC>
		<REACTIVA1INC>39</REACTIVA1INC>
		<REACTIVA2INC>0</REACTIVA2INC>
		<REACTIVA3INC>0</REACTIVA3INC>
		<REACTIVA4INC>0</REACTIVA4INC>
		<FLAGS>0</FLAGS>
	</CURVA>
	<CURVA>
		<CUPS>ES0031405299528001AY0F</CUPS>
		<CLIENTE>1680</CLIENTE>
		<PERIODOMEDIDA>60</PERIODOMEDIDA>
		<FECHAMED>2018-01-13 17:00:00.000</FECHAMED>
		<ACTIVAEINC>66</ACTIVAEINC>
		<ACTIVASINC>0</ACTIVASINC>
		<REACTIVA1INC>39</REACTIVA1INC>
		<REACTIVA2INC>0</REACTIVA2INC>
		<REACTIVA3INC>0</REACTIVA3INC>
		<REACTIVA4INC>0</REACTIVA4INC>
		<FLAGS>0</FLAGS>
	</CURVA>
	<CURVA>
		<CUPS>ES0031405299528001AY0F</CUPS>
		<CLIENTE>1680</CLIENTE>
		<PERIODOMEDIDA>60</PERIODOMEDIDA>
		<FECHAMED>2018-01-13 18:00:00.000</FECHAMED>
		<ACTIVAEINC>60</ACTIVAEINC>
		<ACTIVASINC>0</ACTIVASINC>
		<REACTIVA1INC>38</REACTIVA1INC>
		<REACTIVA2INC>0</REACTIVA2INC>
		<REACTIVA3INC>0</REACTIVA3INC>
		<REACTIVA4INC>0</REACTIVA4INC>
		<FLAGS>0</FLAGS>
	</CURVA>
	<CURVA>
		<CUPS>ES0031405299528001AY0F</CUPS>
		<CLIENTE>1680</CLIENTE>
		<PERIODOMEDIDA>60</PERIODOMEDIDA>
		<FECHAMED>2018-01-13 19:00:00.000</FECHAMED>
		<ACTIVAEINC>63</ACTIVAEINC>
		<ACTIVASINC>0</ACTIVASINC>
		<REACTIVA1INC>39</REACTIVA1INC>
		<REACTIVA2INC>0</REACTIVA2INC>
		<REACTIVA3INC>0</REACTIVA3INC>
		<REACTIVA4INC>0</REACTIVA4INC>
		<FLAGS>0</FLAGS>
	</CURVA>
	<CURVA>
		<CUPS>ES0031405299528001AY0F</CUPS>
		<CLIENTE>1680</CLIENTE>
		<PERIODOMEDIDA>60</PERIODOMEDIDA>
		<FECHAMED>2018-01-13 20:00:00.000</FECHAMED>
		<ACTIVAEINC>65</ACTIVAEINC>
		<ACTIVASINC>0</ACTIVASINC>
		<REACTIVA1INC>39</REACTIVA1INC>
		<REACTIVA2INC>0</REACTIVA2INC>
		<REACTIVA3INC>0</REACTIVA3INC>
		<REACTIVA4INC>0</REACTIVA4INC>
		<FLAGS>0</FLAGS>
	</CURVA>
	<CURVA>
		<CUPS>ES0031405299528001AY0F</CUPS>
		<CLIENTE>1680</CLIENTE>
		<PERIODOMEDIDA>60</PERIODOMEDIDA>
		<FECHAMED>2018-01-13 21:00:00.000</FECHAMED>
		<ACTIVAEINC>65</ACTIVAEINC>
		<ACTIVASINC>0</ACTIVASINC>
		<REACTIVA1INC>41</REACTIVA1INC>
		<REACTIVA2INC>0</REACTIVA2INC>
		<REACTIVA3INC>0</REACTIVA3INC>
		<REACTIVA4INC>0</REACTIVA4INC>
		<FLAGS>0</FLAGS>
	</CURVA>
	<CURVA>
		<CUPS>ES0031405299528001AY0F</CUPS>
		<CLIENTE>1680</CLIENTE>
		<PERIODOMEDIDA>60</PERIODOMEDIDA>
		<FECHAMED>2018-01-13 22:00:00.000</FECHAMED>
		<ACTIVAEINC>67</ACTIVAEINC>
		<ACTIVASINC>0</ACTIVASINC>
		<REACTIVA1INC>39</REACTIVA1INC>
		<REACTIVA2INC>0</REACTIVA2INC>
		<REACTIVA3INC>0</REACTIVA3INC>
		<REACTIVA4INC>0</REACTIVA4INC>
		<FLAGS>0</FLAGS>
	</CURVA>
	<CURVA>
		<CUPS>ES0031405299528001AY0F</CUPS>
		<CLIENTE>1680</CLIENTE>
		<PERIODOMEDIDA>60</PERIODOMEDIDA>
		<FECHAMED>2018-01-13 23:00:00.000</FECHAMED>
		<ACTIVAEINC>65</ACTIVAEINC>
		<ACTIVASINC>0</ACTIVASINC>
		<REACTIVA1INC>41</REACTIVA1INC>
		<REACTIVA2INC>0</REACTIVA2INC>
		<REACTIVA3INC>0</REACTIVA3INC>
		<REACTIVA4INC>0</REACTIVA4INC>
		<FLAGS>0</FLAGS>
	</CURVA>
	<CURVA>
		<CUPS>ES0031405299528001AY0F</CUPS>
		<CLIENTE>1680</CLIENTE>
		<PERIODOMEDIDA>60</PERIODOMEDIDA>
		<FECHAMED>2018-01-14 00:00:00.000</FECHAMED>
		<ACTIVAEINC>63</ACTIVAEINC>
		<ACTIVASINC>0</ACTIVASINC>
		<REACTIVA1INC>41</REACTIVA1INC>
		<REACTIVA2INC>0</REACTIVA2INC>
		<REACTIVA3INC>0</REACTIVA3INC>
		<REACTIVA4INC>0</REACTIVA4INC>
		<FLAGS>0</FLAGS>
	</CURVA>
</CURVAS>
