<?xml version="1.0" encoding="UTF-8"?>
<CURVAS>
	<CURVA>
		<CUPS>ES0031406170741001ZP0F</CUPS>
		<CLIENTE>1681</CLIENTE>
		<PERIODOMEDIDA>60</PERIODOMEDIDA>
		<FECHAMED>2018-01-08 01:00:00.000</FECHAMED>
		<ACTIVAEINC>65</ACTIVAEINC>
		<ACTIVASINC>0</ACTIVASINC>
		<REACTIVA1INC>22</REACTIVA1INC>
		<REACTIVA2INC>0</REACTIVA2INC>
		<REACTIVA3INC>0</REACTIVA3INC>
		<REACTIVA4INC>0</REACTIVA4INC>
		<FLAGS>0</FLAGS>
	</CURVA>
	<CURVA>
		<CUPS>ES0031406170741001ZP0F</CUPS>
		<CLIENTE>1681</CLIENTE>
		<PERIODOMEDIDA>60</PERIODOMEDIDA>
		<FECHAMED>2018-01-08 02:00:00.000</FECHAMED>
		<ACTIVAEINC>59</ACTIVAEINC>
		<ACTIVASINC>0</ACTIVASINC>
		<REACTIVA1INC>21</REACTIVA1INC>
		<REACTIVA2INC>0</REACTIVA2INC>
		<REACTIVA3INC>0</REACTIVA3INC>
		<REACTIVA4INC>0</REACTIVA4INC>
		<FLAGS>0</FLAGS>
	</CURVA>
	<CURVA>
		<CUPS>ES0031406170741001ZP0F</CUPS>
		<CLIENTE>1681</CLIENTE>
		<PERIODOMEDIDA>60</PERIODOMEDIDA>
		<FECHAMED>2018-01-08 03:00:00.000</FECHAMED>
		<ACTIVAEINC>53</ACTIVAEINC>
		<ACTIVASINC>0</ACTIVASINC>
		<REACTIVA1INC>21</REACTIVA1INC>
		<REACTIVA2INC>0</REACTIVA2INC>
		<REACTIVA3INC>0</REACTIVA3INC>
		<REACTIVA4INC>0</REACTIVA4INC>
		<FLAGS>0</FLAGS>
	</CURVA>
	<CURVA>
		<CUPS>ES0031406170741001ZP0F</CUPS>
		<CLIENTE>1681</CLIENTE>
		<PERIODOMEDIDA>60</PERIODOMEDIDA>
		<FECHAMED>2018-01-08 04:00:00.000</FECHAMED>
		<ACTIVAEINC>43</ACTIVAEINC>
		<ACTIVASINC>0</ACTIVASINC>
		<REACTIVA1INC>17</REACTIVA1INC>
		<REACTIVA2INC>1</REACTIVA2INC>
		<REACTIVA3INC>0</REACTIVA3INC>
		<REACTIVA4INC>0</REACTIVA4INC>
		<FLAGS>0</FLAGS>
	</CURVA>
	<CURVA>
		<CUPS>ES0031406170741001ZP0F</CUPS>
		<CLIENTE>1681</CLIENTE>
		<PERIODOMEDIDA>60</PERIODOMEDIDA>
		<FECHAMED>2018-01-08 05:00:00.000</FECHAMED>
		<ACTIVAEINC>16</ACTIVAEINC>
		<ACTIVASINC>0</ACTIVASINC>
		<REACTIVA1INC>0</REACTIVA1INC>
		<REACTIVA2INC>7</REACTIVA2INC>
		<REACTIVA3INC>0</REACTIVA3INC>
		<REACTIVA4INC>0</REACTIVA4INC>
		<FLAGS>0</FLAGS>
	</CURVA>
	<CURVA>
		<CUPS>ES0031406170741001ZP0F</CUPS>
		<CLIENTE>1681</CLIENTE>
		<PERIODOMEDIDA>60</PERIODOMEDIDA>
		<FECHAMED>2018-01-08 06:00:00.000</FECHAMED>
		<ACTIVAEINC>15</ACTIVAEINC>
		<ACTIVASINC>0</ACTIVASINC>
		<REACTIVA1INC>0</REACTIVA1INC>
		<REACTIVA2INC>7</REACTIVA2INC>
		<REACTIVA3INC>0</REACTIVA3INC>
		<REACTIVA4INC>0</REACTIVA4INC>
		<FLAGS>0</FLAGS>
	</CURVA>
	<CURVA>
		<CUPS>ES0031406170741001ZP0F</CUPS>
		<CLIENTE>1681</CLIENTE>
		<PERIODOMEDIDA>60</PERIODOMEDIDA>
		<FECHAMED>2018-01-08 07:00:00.000</FECHAMED>
		<ACTIVAEINC>16</ACTIVAEINC>
		<ACTIVASINC>0</ACTIVASINC>
		<REACTIVA1INC>0</REACTIVA1INC>
		<REACTIVA2INC>6</REACTIVA2INC>
		<REACTIVA3INC>0</REACTIVA3INC>
		<REACTIVA4INC>0</REACTIVA4INC>
		<FLAGS>0</FLAGS>
	</CURVA>
	<CURVA>
		<CUPS>ES0031406170741001ZP0F</CUPS>
		<CLIENTE>1681</CLIENTE>
		<PERIODOMEDIDA>60</PERIODOMEDIDA>
		<FECHAMED>2018-01-08 08:00:00.000</FECHAMED>
		<ACTIVAEINC>18</ACTIVAEINC>
		<ACTIVASINC>0</ACTIVASINC>
		<REACTIVA1INC>3</REACTIVA1INC>
		<REACTIVA2INC>0</REACTIVA2INC>
		<REACTIVA3INC>0</REACTIVA3INC>
		<REACTIVA4INC>0</REACTIVA4INC>
		<FLAGS>0</FLAGS>
	</CURVA>
	<CURVA>
		<CUPS>ES0031406170741001ZP0F</CUPS>
		<CLIENTE>1681</CLIENTE>
		<PERIODOMEDIDA>60</PERIODOMEDIDA>
		<FECHAMED>2018-01-08 09:00:00.000</FECHAMED>
		<ACTIVAEINC>18</ACTIVAEINC>
		<ACTIVASINC>0</ACTIVASINC>
		<REACTIVA1INC>2</REACTIVA1INC>
		<REACTIVA2INC>1</REACTIVA2INC>
		<REACTIVA3INC>0</REACTIVA3INC>
		<REACTIVA4INC>0</REACTIVA4INC>
		<FLAGS>0</FLAGS>
	</CURVA>
	<CURVA>
		<CUPS>ES0031406170741001ZP0F</CUPS>
		<CLIENTE>1681</CLIENTE>
		<PERIODOMEDIDA>60</PERIODOMEDIDA>
		<FECHAMED>2018-01-08 10:00:00.000</FECHAMED>
		<ACTIVAEINC>24</ACTIVAEINC>
		<ACTIVASINC>0</ACTIVASINC>
		<REACTIVA1INC>4</REACTIVA1INC>
		<REACTIVA2INC>0</REACTIVA2INC>
		<REACTIVA3INC>0</REACTIVA3INC>
		<REACTIVA4INC>0</REACTIVA4INC>
		<FLAGS>0</FLAGS>
	</CURVA>
	<CURVA>
		<CUPS>ES0031406170741001ZP0F</CUPS>
		<CLIENTE>1681</CLIENTE>
		<PERIODOMEDIDA>60</PERIODOMEDIDA>
		<FECHAMED>2018-01-08 11:00:00.000</FECHAMED>
		<ACTIVAEINC>25</ACTIVAEINC>
		<ACTIVASINC>0</ACTIVASINC>
		<REACTIVA1INC>3</REACTIVA1INC>
		<REACTIVA2INC>0</REACTIVA2INC>
		<REACTIVA3INC>0</REACTIVA3INC>
		<REACTIVA4INC>0</REACTIVA4INC>
		<FLAGS>0</FLAGS>
	</CURVA>
	<CURVA>
		<CUPS>ES0031406170741001ZP0F</CUPS>
		<CLIENTE>1681</CLIENTE>
		<PERIODOMEDIDA>60</PERIODOMEDIDA>
		<FECHAMED>2018-01-08 12:00:00.000</FECHAMED>
		<ACTIVAEINC>24</ACTIVAEINC>
		<ACTIVASINC>0</ACTIVASINC>
		<REACTIVA1INC>4</REACTIVA1INC>
		<REACTIVA2INC>0</REACTIVA2INC>
		<REACTIVA3INC>0</REACTIVA3INC>
		<REACTIVA4INC>0</REACTIVA4INC>
		<FLAGS>0</FLAGS>
	</CURVA>
	<CURVA>
		<CUPS>ES0031406170741001ZP0F</CUPS>
		<CLIENTE>1681</CLIENTE>
		<PERIODOMEDIDA>60</PERIODOMEDIDA>
		<FECHAMED>2018-01-08 13:00:00.000</FECHAMED>
		<ACTIVAEINC>47</ACTIVAEINC>
		<ACTIVASINC>0</ACTIVASINC>
		<REACTIVA1INC>13</REACTIVA1INC>
		<REACTIVA2INC>0</REACTIVA2INC>
		<REACTIVA3INC>0</REACTIVA3INC>
		<REACTIVA4INC>0</REACTIVA4INC>
		<FLAGS>0</FLAGS>
	</CURVA>
	<CURVA>
		<CUPS>ES0031406170741001ZP0F</CUPS>
		<CLIENTE>1681</CLIENTE>
		<PERIODOMEDIDA>60</PERIODOMEDIDA>
		<FECHAMED>2018-01-08 14:00:00.000</FECHAMED>
		<ACTIVAEINC>73</ACTIVAEINC>
		<ACTIVASINC>0</ACTIVASINC>
		<REACTIVA1INC>22</REACTIVA1INC>
		<REACTIVA2INC>0</REACTIVA2INC>
		<REACTIVA3INC>0</REACTIVA3INC>
		<REACTIVA4INC>0</REACTIVA4INC>
		<FLAGS>0</FLAGS>
	</CURVA>
	<CURVA>
		<CUPS>ES0031406170741001ZP0F</CUPS>
		<CLIENTE>1681</CLIENTE>
		<PERIODOMEDIDA>60</PERIODOMEDIDA>
		<FECHAMED>2018-01-08 15:00:00.000</FECHAMED>
		<ACTIVAEINC>76</ACTIVAEINC>
		<ACTIVASINC>0</ACTIVASINC>
		<REACTIVA1INC>21</REACTIVA1INC>
		<REACTIVA2INC>0</REACTIVA2INC>
		<REACTIVA3INC>0</REACTIVA3INC>
		<REACTIVA4INC>0</REACTIVA4INC>
		<FLAGS>0</FLAGS>
	</CURVA>
	<CURVA>
		<CUPS>ES0031406170741001ZP0F</CUPS>
		<CLIENTE>1681</CLIENTE>
		<PERIODOMEDIDA>60</PERIODOMEDIDA>
		<FECHAMED>2018-01-08 16:00:00.000</FECHAMED>
		<ACTIVAEINC>63</ACTIVAEINC>
		<ACTIVASINC>0</ACTIVASINC>
		<REACTIVA1INC>18</REACTIVA1INC>
		<REACTIVA2INC>0</REACTIVA2INC>
		<REACTIVA3INC>0</REACTIVA3INC>
		<REACTIVA4INC>0</REACTIVA4INC>
		<FLAGS>0</FLAGS>
	</CURVA>
	<CURVA>
		<CUPS>ES0031406170741001ZP0F</CUPS>
		<CLIENTE>1681</CLIENTE>
		<PERIODOMEDIDA>60</PERIODOMEDIDA>
		<FECHAMED>2018-01-08 17:00:00.000</FECHAMED>
		<ACTIVAEINC>49</ACTIVAEINC>
		<ACTIVASINC>0</ACTIVASINC>
		<REACTIVA1INC>19</REACTIVA1INC>
		<REACTIVA2INC>0</REACTIVA2INC>
		<REACTIVA3INC>0</REACTIVA3INC>
		<REACTIVA4INC>0</REACTIVA4INC>
		<FLAGS>0</FLAGS>
	</CURVA>
	<CURVA>
		<CUPS>ES0031406170741001ZP0F</CUPS>
		<CLIENTE>1681</CLIENTE>
		<PERIODOMEDIDA>60</PERIODOMEDIDA>
		<FECHAMED>2018-01-08 18:00:00.000</FECHAMED>
		<ACTIVAEINC>58</ACTIVAEINC>
		<ACTIVASINC>0</ACTIVASINC>
		<REACTIVA1INC>19</REACTIVA1INC>
		<REACTIVA2INC>0</REACTIVA2INC>
		<REACTIVA3INC>0</REACTIVA3INC>
		<REACTIVA4INC>0</REACTIVA4INC>
		<FLAGS>0</FLAGS>
	</CURVA>
	<CURVA>
		<CUPS>ES0031406170741001ZP0F</CUPS>
		<CLIENTE>1681</CLIENTE>
		<PERIODOMEDIDA>60</PERIODOMEDIDA>
		<FECHAMED>2018-01-08 19:00:00.000</FECHAMED>
		<ACTIVAEINC>72</ACTIVAEINC>
		<ACTIVASINC>0</ACTIVASINC>
		<REACTIVA1INC>19</REACTIVA1INC>
		<REACTIVA2INC>0</REACTIVA2INC>
		<REACTIVA3INC>0</REACTIVA3INC>
		<REACTIVA4INC>0</REACTIVA4INC>
		<FLAGS>0</FLAGS>
	</CURVA>
	<CURVA>
		<CUPS>ES0031406170741001ZP0F</CUPS>
		<CLIENTE>1681</CLIENTE>
		<PERIODOMEDIDA>60</PERIODOMEDIDA>
		<FECHAMED>2018-01-08 20:00:00.000</FECHAMED>
		<ACTIVAEINC>50</ACTIVAEINC>
		<ACTIVASINC>0</ACTIVASINC>
		<REACTIVA1INC>18</REACTIVA1INC>
		<REACTIVA2INC>0</REACTIVA2INC>
		<REACTIVA3INC>0</REACTIVA3INC>
		<REACTIVA4INC>0</REACTIVA4INC>
		<FLAGS>0</FLAGS>
	</CURVA>
	<CURVA>
		<CUPS>ES0031406170741001ZP0F</CUPS>
		<CLIENTE>1681</CLIENTE>
		<PERIODOMEDIDA>60</PERIODOMEDIDA>
		<FECHAMED>2018-01-08 21:00:00.000</FECHAMED>
		<ACTIVAEINC>48</ACTIVAEINC>
		<ACTIVASINC>0</ACTIVASINC>
		<REACTIVA1INC>19</REACTIVA1INC>
		<REACTIVA2INC>0</REACTIVA2INC>
		<REACTIVA3INC>0</REACTIVA3INC>
		<REACTIVA4INC>0</REACTIVA4INC>
		<FLAGS>0</FLAGS>
	</CURVA>
	<CURVA>
		<CUPS>ES0031406170741001ZP0F</CUPS>
		<CLIENTE>1681</CLIENTE>
		<PERIODOMEDIDA>60</PERIODOMEDIDA>
		<FECHAMED>2018-01-08 22:00:00.000</FECHAMED>
		<ACTIVAEINC>69</ACTIVAEINC>
		<ACTIVASINC>0</ACTIVASINC>
		<REACTIVA1INC>21</REACTIVA1INC>
		<REACTIVA2INC>0</REACTIVA2INC>
		<REACTIVA3INC>0</REACTIVA3INC>
		<REACTIVA4INC>0</REACTIVA4INC>
		<FLAGS>0</FLAGS>
	</CURVA>
	<CURVA>
		<CUPS>ES0031406170741001ZP0F</CUPS>
		<CLIENTE>1681</CLIENTE>
		<PERIODOMEDIDA>60</PERIODOMEDIDA>
		<FECHAMED>2018-01-08 23:00:00.000</FECHAMED>
		<ACTIVAEINC>60</ACTIVAEINC>
		<ACTIVASINC>0</ACTIVASINC>
		<REACTIVA1INC>18</REACTIVA1INC>
		<REACTIVA2INC>0</REACTIVA2INC>
		<REACTIVA3INC>0</REACTIVA3INC>
		<REACTIVA4INC>0</REACTIVA4INC>
		<FLAGS>0</FLAGS>
	</CURVA>
	<CURVA>
		<CUPS>ES0031406170741001ZP0F</CUPS>
		<CLIENTE>1681</CLIENTE>
		<PERIODOMEDIDA>60</PERIODOMEDIDA>
		<FECHAMED>2018-01-09 00:00:00.000</FECHAMED>
		<ACTIVAEINC>47</ACTIVAEINC>
		<ACTIVASINC>0</ACTIVASINC>
		<REACTIVA1INC>18</REACTIVA1INC>
		<REACTIVA2INC>0</REACTIVA2INC>
		<REACTIVA3INC>0</REACTIVA3INC>
		<REACTIVA4INC>0</REACTIVA4INC>
		<FLAGS>0</FLAGS>
	</CURVA>
</CURVAS>
